set_algebra/__init__.py
set_algebra/endpoint.py
set_algebra/infinity.py
set_algebra/interval.py
set_algebra/parse_interval.py
set_algebra/parser.py
set_algebra/set_.py
set_algebra-0.3.5.dist-info/METADATA
set_algebra-0.3.5.dist-info/RECORD
set_algebra-0.3.5.dist-info/WHEEL
set_algebra-0.3.5.dist-info/top_level.txt
