Metadata-Version: 2.1
Name: set-algebra
Version: 0.3.5
Summary: Algebra of Sets
Home-page: https://github.com/blackelk/set_algebra
Author: Constantine Parkhimovich
Author-email: cparkhimovich@gmail.com
License: MIT
Keywords: math set interval
Platform: UNKNOWN
Classifier: Development Status :: 4 - Beta
Classifier: Intended Audience :: Developers
Classifier: Natural Language :: English
Classifier: License :: OSI Approved :: MIT License
Classifier: Operating System :: OS Independent
Classifier: Programming Language :: Python
Classifier: Programming Language :: Python :: 2.7
Classifier: Programming Language :: Python :: 3.2
Classifier: Programming Language :: Python :: 3.3
Classifier: Programming Language :: Python :: 3.4
Classifier: Programming Language :: Python :: 3.5
Classifier: Programming Language :: Python :: 3.6
Classifier: Topic :: Software Development :: Libraries :: Python Modules
